NSum/NSUM_2fsm/design.sv
// input 3 bit, output 4 bit
module NSum(
  input [2:0] N,
  input N_valid,
  input reset,
  input clk,
  output reg [3:0] sum,
  output reg sum_valid
);

  reg [2:0] i;
  wire [2:0] in_mux;
  wire [3:0] add_out;
  wire [3:0] sum_mux;
  wire i_eq_1;
  reg state; // States Idle and Busy
  parameter idle = 0, busy = 1;
  
  // **** Combinational Part *** //
  
  // Input mux part
  assign in_mux = state ? (i-1):N ;
  // Adder part
  assign add_out = sum + i;
  // Sum block part
  assign sum_mux =  state ? add_out : 4'b0000 ;
  // sum valid before one clock cycle
  assign i_eq_1 = (i==1);
  
  // **** Sequential Part *** //
  always @(posedge clk)
    begin
      if(reset)state <= idle;
      // i reg
      i <= in_mux;
      // sum reg
      sum <= sum_mux;
      // output qualifier
      sum_valid <= i_eq_1;

      //State Update 	
      case (state)
        busy: state <= i_eq_1 ? idle : busy;
        idle: state <= N_valid ? busy : idle;
      endcase
        
    end
endmodule

NSum/NSUM_2fsm/testbench.sv
module NSum_tb;
  reg [2:0] N;
  reg N_valid;
  reg reset;
  reg clk;
  wire [3:0] sum;
  wire sum_valid;

  NSum uut ( .N(N), .N_valid(N_valid), .reset(reset), 					.clk(clk), .sum(sum),.sum_valid(sum_valid)
           );

  initial begin
    $dumpfile("NSum.vcd");
    $dumpvars(0);
  end

  // Clock 
  initial begin
    clk = 1;
    forever #5 clk = ~clk; // 10ns clock 
  end

  initial begin
    N_valid = 0;
    reset = 0;

    // Initial Reset
    #2 reset = 1; 
    #10 reset = 0;

    // Apply N = 3
    #5 N = 5; N_valid = 1;
    #10 N_valid = 0;
	#20  N = 4; N_valid = 1;
    #10 N_valid = 0;
    #200
    $finish;
  end
endmodule

NSum/NSUM_2fsm/NSum.vcd
$date
	Sat Feb  8 13:18:07 2025
$end
$version
	Icarus Verilog
$end
$timescale
	1s
$end
$scope module NSum_tb $end
$var wire 1 ! sum_valid $end
$var wire 4 " sum [3:0] $end
$var reg 3 # N [2:0] $end
$var reg 1 $ N_valid $end
$var reg 1 % clk $end
$var reg 1 & reset $end
$scope module uut $end
$var wire 3 ' N [2:0] $end
$var wire 1 $ N_valid $end
$var wire 1 % clk $end
$var wire 1 & reset $end
$var wire 4 ( sum_mux [3:0] $end
$var wire 3 ) in_mux [2:0] $end
$var wire 1 * i_eq_1 $end
$var wire 4 + add_out [3:0] $end
$var parameter 32 , busy $end
$var parameter 32 - idle $end
$var reg 3 . i [2:0] $end
$var reg 1 / state $end
$var reg 4 0 sum [3:0] $end
$var reg 1 ! sum_valid $end
$upscope $end
$upscope $end
$enddefinitions $end
$comment Show the parameter values. $end
$dumpall
b0 -
b1 ,
$end
#0
$dumpvars
bx 0
x/
bx .
bx +
x*
bx )
bx (
bx '
0&
1%
0$
bx #
bx "
x!
$end
#2
1&
#5
0%
#10
b0 (
0/
1%
#12
0&
#15
0%
#17
b101 )
1$
b101 #
b101 '
#20
b100 )
b101 (
1/
b101 +
b0 "
b0 0
0*
b101 .
1%
#25
0%
#27
0$
#30
b11 )
b1001 (
0!
b101 "
b101 0
b1001 +
b100 .
1%
#35
0%
#40
b10 )
b1100 (
b1001 "
b1001 0
b1100 +
b11 .
1%
#45
0%
#47
1$
b100 #
b100 '
#50
b1 )
b1110 (
b1100 "
b1100 0
b1110 +
b10 .
1%
#55
0%
#57
0$
#60
b0 )
b1111 (
b1110 "
b1110 0
b1111 +
1*
b1 .
1%
#65
0%
#70
b100 )
b0 (
0/
1!
b1111 "
b1111 0
b1111 +
0*
b0 .
1%
#75
0%
#80
0!
b0 "
b0 0
b100 +
b100 .
1%
