NSum/NSUM_3fsm/design.sv
// input 3 bit, output 4 bit
module NSum(
  input [2:0] N,
  input N_valid,
  input reset,
  input clk,
  input Ack,
  output reg [3:0] sum,
  output reg sum_valid
);

  reg [2:0] i;
  wire [2:0] in_mux;
  wire [3:0] add_out;
  wire [3:0] sum_mux;
  wire i_eq_1;
  reg [1:0] state; // States Idle and Busy
  parameter idle = 2'b00, 
  			busy = 2'b01,
  			done = 2'b10 ;
  
  // **** Combinational Part *** //
  
  // Input mux part
  assign in_mux = state[0] ? (i-1):N ;
  // Adder part
  assign add_out = sum + i;
  // sum valid before one clock cycle
  assign i_eq_1 = (i==1);
  // Sum block part
  assign sum_mux = (state == idle) ? 4'b0 : (state == busy) ? add_out :
                 (state == done) ? sum : 4'b0;
  
  // **** Sequential Part *** //
  always @(posedge clk)
    begin
      if(reset)state <= idle;
      // i reg
      i <= in_mux;
      // sum reg
      sum <= sum_mux;
      // output qualifier
      sum_valid <= (state == done)?1'b1:1'b0 ;

      //State Update 	
      case (state)
        busy: state <= i_eq_1 ? done : busy;
        idle: state <= N_valid ? busy : idle;
        done: state <= Ack ? idle : done;
      endcase   
    end
endmodule

NSum/NSUM_3fsm/testbench.sv
module NSum_tb;
  reg [2:0] N;
  reg N_valid;
  reg reset;
  reg clk;
  reg Ack;  // Changed to reg
  wire [3:0] sum;
  wire sum_valid;

  // Instantiate the NSum module
  NSum uut (
    .N(N), 
    .N_valid(N_valid), 
    .reset(reset), 
    .clk(clk), 
    .sum(sum),
    .sum_valid(sum_valid), 
    .Ack(Ack)
  );

  initial begin
    $dumpfile("NSum.vcd");
    $dumpvars(0, NSum_tb); // Dump variables
  end

  // Clock Generation
  initial begin
    clk = 1;
    forever #5 clk = ~clk; // 10ns clock
  end

  initial begin
    // Initialize Inputs
    N_valid = 0;
    reset = 0;
    Ack = 0;

    // Initial Reset
    #2 reset = 1; 
    #10 reset = 0;

    // Apply N = 5
    #5 N = 5; N_valid = 1;
    #10 N_valid = 0;
    #20 N = 4; N_valid = 1;
    #10 N_valid = 0;

    // Acknowledge after 200ns
    #100 Ack = 1;
	#10 Ack = 0;
    #50 $finish;
  end
endmodule

NSum/NSUM_3fsm/NSum.vcd
$date
	Sat Feb  8 13:18:27 2025
$end
$version
	Icarus Verilog
$end
$timescale
	1s
$end
$scope module NSum_tb $end
$var wire 1 ! sum_valid $end
$var wire 4 " sum [3:0] $end
$var reg 1 # Ack $end
$var reg 3 $ N [2:0] $end
$var reg 1 % N_valid $end
$var reg 1 & clk $end
$var reg 1 ' reset $end
$scope module uut $end
$var wire 1 # Ack $end
$var wire 3 ( N [2:0] $end
$var wire 1 % N_valid $end
$var wire 1 & clk $end
$var wire 1 ' reset $end
$var wire 4 ) sum_mux [3:0] $end
$var wire 3 * in_mux [2:0] $end
$var wire 1 + i_eq_1 $end
$var wire 4 , add_out [3:0] $end
$var parameter 2 - busy $end
$var parameter 2 . done $end
$var parameter 2 / idle $end
$var reg 3 0 i [2:0] $end
$var reg 2 1 state [1:0] $end
$var reg 4 2 sum [3:0] $end
$var reg 1 ! sum_valid $end
$upscope $end
$upscope $end
$enddefinitions $end
$comment Show the parameter values. $end
$dumpall
b0 /
b10 .
b1 -
$end
#0
$dumpvars
bx 2
bx 1
bx 0
bx ,
x+
bx *
bx )
bx (
0'
1&
0%
bx $
0#
bx "
x!
$end
#2
1'
#5
0&
#10
b0 )
b0 1
1&
#12
0'
#15
0&
#17
b101 *
1%
b101 $
b101 (
#20
b100 *
b101 )
b1 1
0!
b101 ,
b0 "
b0 2
0+
b101 0
1&
#25
0&
#27
0%
#30
b1001 )
b11 *
b101 "
b101 2
b1001 ,
b100 0
1&
#35
0&
#40
b1100 )
b10 *
b1001 "
b1001 2
b1100 ,
b11 0
1&
#45
0&
#47
1%
b100 $
b100 (
#50
b1110 )
b1 *
b1100 "
b1100 2
b1110 ,
b10 0
1&
#55
0&
#57
0%
#60
b1111 )
b0 *
b1110 "
b1110 2
b1111 ,
1+
b1 0
1&
#65
0&
#70
b1111 )
b100 *
b10 1
b1111 "
b1111 2
b1111 ,
0+
b0 0
1&
#75
0&
#80
1!
b11 ,
b100 0
1&
#85
0&
#90
1&
#95
0&
#100
1&
#105
0&
#110
1&
#115
0&
#120
1&
#125
0&
#130
1&
#135
0&
#140
1&
#145
0&
#150
1&
#155
0&
#157
1#
#160
b0 )
b0 1
1&
#165
0&
#167
0#
#170
0!
b100 ,
b0 "
b0 2
1&
