NSum/NSUM_wofsm/design.sv
// Input 3 bit, output 4 bit
module NSum(
  input [2:0] N,
  input N_valid,
  input clk,
  output reg [3:0] sum,
  output reg sum_valid
);

  reg [2:0] i;
  wire [2:0] in_mux;
  wire [3:0] add_out;
  wire [3:0] sum_mux;
  wire i_eq_1;
  
  // **** Combinational Part *** //
  
  // Input mux part
  assign in_mux = N_valid ? N: (i-1);
  // Adder part
  assign add_out = sum + i;
  // Sum block part
  assign sum_mux =  N_valid ? 4'b0000 : add_out;
  // sum valid before one clock cycle
  assign i_eq_1 = (i==1);
 
  
  // **** Sequential Part *** //
  always @(posedge clk)
    begin
      // i reg
      i <= in_mux;
      // sum reg
      sum <= sum_mux;
      // output qualifier
      sum_valid <= i_eq_1;      
    end
endmodule

NSum/NSUM_wofsm/testbench.sv
module NSum_tb;
  reg [2:0] N;
  reg N_valid;
  reg reset;
  reg clk;
  wire [3:0] sum;
  wire sum_valid;

  NSum uut ( .N(N), .N_valid(N_valid), .clk(clk), .sum(sum),.sum_valid(sum_valid)
           );

  initial begin
    $dumpfile("NSum.vcd");
    $dumpvars(0);
  end

  // Clock 
  initial begin
    clk = 1;
    forever #5 clk = ~clk; // 10ns clock 
  end

  initial begin
    N_valid = 0;

    // Apply N = 5
    #5 N = 5; N_valid = 1;
    #10 N_valid = 0;
	#20  N = 4; N_valid = 1;
    #10 N_valid = 0;
    #200
    $finish;
  end
endmodule

NSum/NSUM_wofsm/NSum.vcd
$date
	Sat Feb  8 13:17:41 2025
$end
$version
	Icarus Verilog
$end
$timescale
	1s
$end
$scope module NSum_tb $end
$var wire 1 ! sum_valid $end
$var wire 4 " sum [3:0] $end
$var reg 3 # N [2:0] $end
$var reg 1 $ N_valid $end
$var reg 1 % clk $end
$scope module uut $end
$var wire 3 & N [2:0] $end
$var wire 1 $ N_valid $end
$var wire 1 % clk $end
$var wire 4 ' sum_mux [3:0] $end
$var wire 3 ( in_mux [2:0] $end
$var wire 1 ) i_eq_1 $end
$var wire 4 * add_out [3:0] $end
$var reg 3 + i [2:0] $end
$var reg 4 , sum [3:0] $end
$var reg 1 ! sum_valid $end
$upscope $end
$upscope $end
$enddefinitions $end
$comment Show the parameter values. $end
$dumpall
$end
#0
$dumpvars
bx ,
bx +
bx *
x)
bx (
bx '
bx &
1%
0$
bx #
bx "
x!
$end
#5
b101 (
b0 '
1$
b101 #
b101 &
0%
#10
b101 *
b0 "
b0 ,
0)
b101 +
1%
#15
b100 (
b101 '
0%
0$
#20
b11 (
b1001 '
0!
b101 "
b101 ,
b1001 *
b100 +
1%
#25
0%
#30
b10 (
b1100 '
b1001 "
b1001 ,
b1100 *
b11 +
1%
#35
b100 (
b0 '
0%
1$
b100 #
b100 &
#40
b0 "
b0 ,
b100 *
b100 +
1%
#45
b11 (
b100 '
0%
0$
#50
b10 (
b111 '
b100 "
b100 ,
b111 *
b11 +
1%
#55
0%
#60
b1 (
b1001 '
b111 "
b111 ,
b1001 *
b10 +
1%
#65
0%
#70
b0 (
b1010 '
b1001 "
b1001 ,
b1010 *
1)
b1 +
1%
#75
0%
#80
b111 (
1!
b1010 "
b1010 ,
b1010 *
0)
b0 +
1%
#85
0%
#90
b110 (
b1 '
0!
b1 *
b111 +
1%
#95
0%
#100
b101 (
b111 '
b1 "
b1 ,
b111 *
b110 +
1%
#105
0%
#110
b100 (
b1100 '
b111 "
b111 ,
b1100 *
b101 +
1%
#115
0%
#120
b11 (
b0 '
b1100 "
b1100 ,
b0 *
b100 +
1%
#125
0%
#130
b10 (
b11 '
b0 "
b0 ,
b11 *
b11 +
1%
#135
0%
#140
b1 (
b101 '
b11 "
b11 ,
b101 *
b10 +
1%
#145
0%
#150
b0 (
b110 '
b101 "
b101 ,
b110 *
1)
b1 +
1%
#155
0%
#160
b111 (
1!
b110 "
b110 ,
b110 *
0)
b0 +
1%
#165
0%
#170
b110 (
b1101 '
0!
b1101 *
b111 +
1%
#175
0%
#180
b101 (
b11 '
b1101 "
b1101 ,
b11 *
b110 +
1%
#185
0%
#190
b100 (
b1000 '
b11 "
b11 ,
b1000 *
b101 +
1%
#195
0%
#200
b11 (
b1100 '
b1000 "
b1000 ,
b1100 *
b100 +
1%
#205
0%
#210
b10 (
b1111 '
b1100 "
b1100 ,
b1111 *
b11 +
1%
#215
0%
#220
b1 (
b1 '
b1111 "
b1111 ,
b1 *
b10 +
1%
#225
0%
#230
b0 (
b10 '
b1 "
b1 ,
b10 *
1)
b1 +
1%
#235
0%
#240
b111 (
1!
b10 "
b10 ,
b10 *
0)
b0 +
1%
